setup.py
distributions_chim/Binomialdistribution.py
distributions_chim/Gaussiandistribution.py
distributions_chim/Generaldistribution.py
distributions_chim/__init__.py
distributions_chim.egg-info/PKG-INFO
distributions_chim.egg-info/SOURCES.txt
distributions_chim.egg-info/dependency_links.txt
distributions_chim.egg-info/not-zip-safe
distributions_chim.egg-info/top_level.txt