Metadata-Version: 1.0
Name: distributions-chim
Version: 0.1
Summary: Gaussian and Binomial distributions
Home-page: UNKNOWN
Author: Tserenchimed Ganbold
Author-email: UNKNOWN
License: UNKNOWN
Platform: UNKNOWN
